LISENCE
README.md
setup.cfg
setup.py
framania/__init__.py
framania.egg-info/PKG-INFO
framania.egg-info/SOURCES.txt
framania.egg-info/dependency_links.txt
framania.egg-info/not-zip-safe
framania.egg-info/requires.txt
framania.egg-info/top_level.txt
framania/daskmania/__init__.py
framania/daskmania/aggregate.py
framania/daskmania/api.py
framania/daskmania/filter.py
framania/daskmania/index.py
framania/daskmania/merge.py
framania/daskmania/meta.py
framania/daskmania/stack.py
framania/daskmania/util.py
framania/hvmania/__init__.py
framania/hvmania/manager.py
framania/hvmania/server.py
framania/intakemania/__init__.py
framania/intakemania/api.py
framania/intakemania/extension.py
framania/intakemania/jupyter.py
framania/intakemania/user_defined_class_parquet_source.py
framania/intakemania/util.py
framania/pandasmania/__init__.py
framania/pandasmania/aggregate.py
framania/pandasmania/api.py
framania/pandasmania/filter.py
framania/pandasmania/merge.py
framania/pandasmania/na.py
framania/pandasmania/stack.py
framania/pandasmania/string.py
framania/pandasmania/transform.py
framania/pandasmania/util.py
test/__init__.py
test/test_api.py
test/test_intakemania_custom_class_paquet_source.py
test/test_intakemania_extension.py