Metadata-Version: 2.1
Name: framania
Version: 0.10.3
Summary: pandas/dask DataFrame API extension library
Home-page: UNKNOWN
Author: Yuki Chiba
Author-email: yuki-chiba@outlook.jp
License: UNKNOWN
Platform: UNKNOWN
License-File: LISENCE
